ascify/__init__.py
ascify/color.py
ascify/grid.py
ascify/renditions.py
ascify-1.0.dist-info/METADATA
ascify-1.0.dist-info/WHEEL
ascify-1.0.dist-info/top_level.txt
ascify-1.0.dist-info/RECORD
