Metadata-Version: 2.1
Name: ascify
Version: 1.0
Summary: Lightweight library for turning images to grid of ascii tokens
Home-page: https://github.com/theonekeyg/ascify
Author: theonekeyg
Author-email: theonekeyg@gmail.com
License: UNKNOWN
Platform: UNKNOWN
Requires-Dist: numpy (>=1.13.0)
Requires-Dist: Pillow (>=6.0)
